pytest_zulip/__init__.py
pytest_zulip/hooks.py
pytest_zulip/plugin.py
pytest_zulip/zulip.py
pytest_zulip/__pycache__/__init__.cpython-310.pyc
pytest_zulip-0.2.1.data/data/pytest_zulip/__init__.cpython-310.pyc
pytest_zulip-0.2.1.dist-info/METADATA
pytest_zulip-0.2.1.dist-info/WHEEL
pytest_zulip-0.2.1.dist-info/entry_points.txt
pytest_zulip-0.2.1.dist-info/top_level.txt
pytest_zulip-0.2.1.dist-info/RECORD
